kairix_devtools/__init__.py
kairix_devtools/__main__.py
kairix_devtools/asyncio/__init__.py
kairix_devtools/asyncio/await_checker.py
kairix_devtools/cli/__init__.py
kairix_devtools/cli/asyncio/__init__.py
kairix_devtools/cli/asyncio/check_await.py
kairix_devtools-25.6.5.dist-info/licenses/LICENSE
kairix_devtools-25.6.5.dist-info/METADATA
kairix_devtools-25.6.5.dist-info/WHEEL
kairix_devtools-25.6.5.dist-info/entry_points.txt
kairix_devtools-25.6.5.dist-info/top_level.txt
kairix_devtools-25.6.5.dist-info/RECORD
