Metadata-Version: 2.4
Name: kairix-devtools
Version: 25.6.5
Summary: Professional Python development tools for async/await analysis and code quality
Author-email: Kairix Devteam <devteam@kairix.dev>
License-Expression: Unlicense
Project-URL: Homepage, https://github.com/kairix-dev/devtools-python
Project-URL: Documentation, https://github.com/kairix-dev/devtools-python/blob/main/docs/README.md
Project-URL: Repository, https://github.com/kairix-dev/devtools-python
Project-URL: Bug Tracker, https://github.com/kairix-dev/devtools-python/issues
Project-URL: Changelog, https://github.com/kairix-dev/devtools-python/blob/main/CHANGELOG.md
Classifier: Development Status :: 4 - Beta
Classifier: Intended Audience :: Developers
Classifier: Operating System :: OS Independent
Classifier: Programming Language :: Python :: 3
Classifier: Programming Language :: Python :: 3.12
Classifier: Topic :: Software Development :: Quality Assurance
Classifier: Topic :: Software Development :: Testing
Classifier: Topic :: Software Development :: Libraries :: Python Modules
Requires-Python: >=3.12
License-File: LICENSE
Requires-Dist: click>=8.0.0
Requires-Dist: pydantic>=2.0.0
Provides-Extra: dev
Requires-Dist: pre-commit; extra == "dev"
Requires-Dist: radon>=6.0.0; extra == "dev"
Provides-Extra: ci
Requires-Dist: black>=23.0.0; extra == "ci"
Requires-Dist: pyright>=1.1.0; extra == "ci"
Requires-Dist: mypy>=1.0.0; extra == "ci"
Requires-Dist: isort>=5.0.0; extra == "ci"
Requires-Dist: autoflake>=2.0.0; extra == "ci"
Requires-Dist: pytest>=7.0.0; extra == "ci"
Requires-Dist: pytest-cov>=4.0.0; extra == "ci"
Dynamic: license-file
